{
  "project_info": {
    "project_number": "773892679617",
    "project_id": "flacronai-c8dab",
    "storage_bucket": "flacronai-c8dab.firebasestorage.app"
  },
  "client": [
    {
      "client_info": {
        "mobilesdk_app_id": "1:773892679617:android:877dc8163d82e4bf957140",
        "android_client_info": {
          "package_name": "com.flacronenterprises.flacronai"
        }
      },
      "oauth_client": [
        {
          "client_id": "773892679617-vfqpcld4aubfdi93rj0bod1uomev8hiu.apps.googleusercontent.com",
          "client_type": 3
        }
      ],
      "api_key": [
        {
          "current_key": "AIzaSyDqKPNYgIvFOASOyjBB9VkNowtBhp1O06k"
        }
      ],
      "services": {
        "appinvite_service": {
          "other_platform_oauth_client": [
            {
              "client_id": "773892679617-vfqpcld4aubfdi93rj0bod1uomev8hiu.apps.googleusercontent.com",
              "client_type": 3
            }
          ]
        }
      }
    }
  ],
  "configuration_version": "1"
}
